aprsd_irc_extension/__init__.py
aprsd_irc_extension/extension.py
aprsd_irc_extension/utils.py
aprsd_irc_extension/cmds/__init__.py
aprsd_irc_extension/cmds/db.py
aprsd_irc_extension/cmds/server.py
aprsd_irc_extension/conf/__init__.py
aprsd_irc_extension/conf/main.py
aprsd_irc_extension/conf/opts.py
aprsd_irc_extension/db/README
aprsd_irc_extension/db/__init__.py
aprsd_irc_extension/db/env.py
aprsd_irc_extension/db/models.py
aprsd_irc_extension/db/script.py.mako
aprsd_irc_extension/db/session.py
aprsd_irc_extension/db/versions/030cab1951e1_.py
aprsd_irc_extension-0.0.5.dist-info/LICENSE
aprsd_irc_extension-0.0.5.dist-info/METADATA
aprsd_irc_extension-0.0.5.dist-info/WHEEL
aprsd_irc_extension-0.0.5.dist-info/entry_points.txt
aprsd_irc_extension-0.0.5.dist-info/pbr.json
aprsd_irc_extension-0.0.5.dist-info/top_level.txt
aprsd_irc_extension-0.0.5.dist-info/RECORD
